{"http://ussd:8092/account/v1/account_opening": {"InstantAccIntiateRequestFuncScreen-RW": {"next_screen": "InstantAccOpenRouterScreen-RW", "menus_that_points_to_this_menu": ["InstantAccountSecondSecurityAnswer-RW", "InstantAccIntiateR-RW"]}}, "http://ussd:8092/account/v1/accountnumber/lookup": {"FtEquityFavoriteNameCheck-RW": {"next_screen": "FtEquityFavNameCheckRouter-RW", "menus_that_points_to_this_menu": []}}, "http://ussd:8092/account/v1/accounts_inquiry_charge": {"FetchMiniStatementInquiryChargesFS-RW": {"next_screen": "FetchMiniStatementInquiryChargesRS-RW", "menus_that_points_to_this_menu": ["MiniStatementAccSelectionScreen-RW"]}}, "http://ussd:8092/account/v1/all_accounts_balances": {"FetchAllAccountBalanceFS-RW": {"next_screen": "AllBalanceRouter-RW", "menus_that_points_to_this_menu": []}}, "http://ussd:8092/account/v1/balance": {"EcoBalanceF-RW": {"next_screen": "MainMenuScreenRW", "menus_that_points_to_this_menu": []}}, "http://ussd:8092/account/v1/balances": {"FetchAllAccountBalance-RW": {"next_screen": "AllBalanceRouter-RW", "menus_that_points_to_this_menu": []}}, "http://ussd:8092/account/v1/complete_account_opening": {"InstantAccCompleteFuncScreen-RW": {"next_screen": "InstantAccCompleteRouterScreen-RW", "menus_that_points_to_this_menu": []}}, "http://ussd:8092/account/v1/emailstatement": {"SendEmailStatementFuncScreen-RW": {"next_screen": "EmailStatementRouterScreeen-RW", "menus_that_points_to_this_menu": []}}, "http://ussd:8092/account/v1/get_secret_question": {"CheckLastLoginFetchSecQuesFunction-RW": {"next_screen": "CheckLastLoginFetchQuestionsRouter-RW", "menus_that_points_to_this_menu": []}}, "http://ussd:8092/account/v1/initiate_pin_reset": {"CheckLastLoginIntermediateFunction-RW": {"next_screen": "CheckLastLoginIntermediateRouter-RW", "menus_that_points_to_this_menu": ["CheckLastLoginIdNumber-RW"]}}, "http://ussd:8092/account/v1/lookup": {"SCAccountLookUpScreen-RW": {"next_screen": "SCAccountLookUpRouter-RW", "menus_that_points_to_this_menu": ["SCRegisteredClientToken-RW"]}}, "http://ussd:8092/account/v1/lookupv1": {"MpesaCheckBalFunction-RW": {"next_screen": "MpesaCheckBalRouter-RW", "menus_that_points_to_this_menu": ["SendMpesaSourceAccount-RW"]}}, "http://ussd:8092/account/v1/ministatement": {"GetMinistatementFuncScreen-RW": {"next_screen": "SendMiniStatementSMS-RW", "menus_that_points_to_this_menu": []}}, "http://ussd:8092/account/v1/refugee_onboarding": {"InstantAccIntiateRefugeeF-RW": {"next_screen": "InstantAccRefugeeOpenR-RW", "menus_that_points_to_this_menu": []}}, "http://ussd:8092/account/v1/single_account_balance": {"FetchSingleAccountBalanceFS-RW": {"next_screen": "FetchSingleAccountBalanceRS-RW", "menus_that_points_to_this_menu": []}}, "http://ussd:8092/account/v1/single_account_mini_statement": {"GetMiniStatementFS-RW": {"next_screen": "GetMiniStatementRS-RW", "menus_that_points_to_this_menu": []}}, "http://ussd:8092/account/v1/user_core_accounts": {"PesaLinkDeregisterGetAccountFunction-RW": {"next_screen": "PesaLinkDeregisGetUserAccountsRouter-RW", "menus_that_points_to_this_menu": []}}, "http://ussd:8092/account/v1/verifyanswers": {"CheckLastLoginVerifyQuestions-RW": {"next_screen": "CheckLastLoginQuestionsVerifyRouter-RW", "menus_that_points_to_this_menu": ["CheckLastLoginQuestionTwoAnswer-RW"]}}, "http://ussd:8092/agent/v1/agent/": {"QueryAgent-RW": {"next_screen": "AgentLookupRouter-RW", "menus_that_points_to_this_menu": ["AgentCodeScreen-RW"]}}, "http://ussd:8092/agent/v1/agent/charges/": {"FetchAgentWithdrawCharges-RW": {"next_screen": "FetchAgentWithdrawChargesRouter-RW", "menus_that_points_to_this_menu": ["AgentAmountScreen-RW"]}}, "http://ussd:8092/agent/v1/agent/withdraw/": {"AgentWithdrawFunction-RW": {"next_screen": "AgentWithdrawRouter-RW", "menus_that_points_to_this_menu": []}}, "http://ussd:8092/airtime/v1/buyAirtime": {"BuyAirtimeFavoutiteFunction-RW": {"next_screen": "BuyAirtimeFavoriteRouter-RW", "menus_that_points_to_this_menu": []}}, "http://ussd:8092/airtime/v1/getTelcos": {"SCFetchAirtimeTelcos-RW": {"next_screen": "SCFetchAirtimeTelcosRouter-RW", "menus_that_points_to_this_menu": []}}, "http://ussd:8092/bills/v1/billerDetails/": {"PayBillFavNameCheck-RW": {"next_screen": "PayBillfavNameCheckRouter-RW", "menus_that_points_to_this_menu": []}}, "http://ussd:8092/bills/v1/charges": {"PayBillFavCharges-RW": {"next_screen": "PayBillFavoriteChargesRouter-RW", "menus_that_points_to_this_menu": []}}, "http://ussd:8092/bills/v1/pay": {"PayFavoriteBillerFunction-RW": {"next_screen": "PayFavBillerRouter-RW", "menus_that_points_to_this_menu": []}}, "http://ussd:8092/bills/v1/popular": {"SCPBFetchPopularBillers-RW": {"next_screen": "SCPBManualBillerCodeIS-RW", "menus_that_points_to_this_menu": ["SCPBMainMenuScreen-RW"]}}, "http://ussd:8092/bills/v1/validate": {"ValidateBillerDetailsPayBillFS": {"next_screen": "ValidateBillerDetailsPayBillRS", "menus_that_points_to_this_menu": []}}, "http://ussd:8092/buyGoods/v1/buyGoods": {"PayGoodsFavouriteFunction-RW": {"next_screen": "PayGoodsFavoriteRouter-RW", "menus_that_points_to_this_menu": []}}, "http://ussd:8092/buyGoods/v1/buyGoodsMpesa": {"PayMpesaTillFunction-RW": {"next_screen": "PayMpesaTillRouter-RW", "menus_that_points_to_this_menu": []}}, "http://ussd:8092/buyGoods/v1/merchant_check": {"BuyGoodsFavNameCheck-RW": {"next_screen": "EazyPayFavNameCheckRouter-RW", "menus_that_points_to_this_menu": ["BuyGoodsFavSelectAccount-RW"]}}, "http://ussd:8092/buyGoods/v1/mpesa/charges": {"FetchMpesaTillTxnCharges-RW": {"next_screen": "MpesaTillChargesRouter-RW", "menus_that_points_to_this_menu": ["PayMpesaSourceAccount-RW"]}}, "http://ussd:8092/buyGoods/v1/nameCheck": {"PayMpesaTillNameCheck-RW": {"next_screen": "MpesaTillNameCheckRouter-RW", "menus_that_points_to_this_menu": ["MpesaTillNumber-RW"]}}, "http://ussd:8092/favourite/v1/add_beneficiary": {"SaveSendMoneyFavorite-RW": {"next_screen": "SendSaveMoneyFavoriteRouter-RW", "menus_that_points_to_this_menu": ["SendMoneyFavAlias-RW"]}}, "http://ussd:8092/favourite/v1/beneficiary": {"CheckLastLoginRemoveFirstQuesFunctio-RW": {"next_screen": "CheckLastLoginDisSecondBatchOfQuest-RW", "menus_that_points_to_this_menu": ["CheckLastLoginQuestionOneAnswer-RW"]}}, "http://ussd:8092/favourite/v1/beneficiary/remove": {"RemoveFavouriteFunction-RW": {"next_screen": "RemoveFavouriteRouter-RW", "menus_that_points_to_this_menu": []}}, "http://ussd:8092/linkAccount/v1/delinkAccount": {"DelinkEquityAccUnlinkFunctionScreen-RW": {"next_screen": "DelinkEquityAccUnlinkRouterScreen-RW", "menus_that_points_to_this_menu": []}}, "http://ussd:8092/linkAccount/v1/getUserAccounts/": {"GetLinkedEquityAccountsFunctionScree-RW": {"next_screen": "EquityLinkedAccsRouterScreen-RW", "menus_that_points_to_this_menu": []}}, "http://ussd:8092/linkAccount/v1/linkAditionalAccounts": {"LinkEquityAccFunctionScreen-RW": {"next_screen": "LinkEquityAccRouter-RW", "menus_that_points_to_this_menu": ["LinkEquityAccUserPinInputScreen-RW"]}}, "http://ussd:8092/loan/v1/apply": {"SalaryLoanApplyFunction-RW": {"next_screen": "SalaryLoanApplyRouter-RW", "menus_that_points_to_this_menu": []}}, "http://ussd:8092/loan/v1/customer_products_query": {"EcoSystemGetLimitFunctions-RW": {"next_screen": "EcoSystemGetLimtsRouter-RW", "menus_that_points_to_this_menu": []}}, "http://ussd:8092/loan/v1/ecopaymentoptions": {"EcoPurchaseOptionsQueryF-RW": {"next_screen": "EcoPurchaseOptionsQueryR-RW", "menus_that_points_to_this_menu": ["EcoLimitnAmountI-RW"]}}, "http://ussd:8092/loan/v1/ecosystem/accept": {"EcoFullPaymentAcceptF-RW": {"next_screen": "EcoFullPaymentAcceptR-RW", "menus_that_points_to_this_menu": []}}, "http://ussd:8092/loan/v1/ecosystem/customerproducts": {"CustomerEcosysF-RW": {"next_screen": "CustomerEcosysR-RW", "menus_that_points_to_this_menu": []}}, "http://ussd:8092/loan/v1/ecosystem/initiate": {"EcoFullpaymentF-RW": {"next_screen": "EcoFullPaymentR-RW", "menus_that_points_to_this_menu": []}}, "http://ussd:8092/loan/v1/ecosystem_acceptloanoffer": {"EcoSystemAcceptOffer-RW": {"next_screen": "EcoSystemAcceptOfferRouter-RW", "menus_that_points_to_this_menu": []}}, "http://ussd:8092/loan/v1/ecosystem_initiateloan": {"EcoSystemIntiateLoanTransaction-RW": {"next_screen": "EcoSystemIntiateLoanRouter-RW", "menus_that_points_to_this_menu": []}}, "http://ussd:8092/loan/v1/ecosystemloanlimitone": {"EcoLimitF-RW": {"next_screen": "EcoLimitR-RW", "menus_that_points_to_this_menu": ["EcosystemLoanSelectAccountMI-RW"]}}, "http://ussd:8092/loan/v1/ecosystempayloan": {"EcoRepaymentF-RW": {"next_screen": "EcoRepaymentR-RW", "menus_that_points_to_this_menu": []}}, "http://ussd:8092/loan/v1/ecoystemtotalrepayable": {"EcoPartialLoanRepayableF-RW": {"next_screen": "EcoPartialLoanRepayableR-RW", "menus_that_points_to_this_menu": ["EcoPartialLoanAmountI-RW"]}}, "http://ussd:8092/loan/v1/fullpayment": {"FullPaymentFunction-RW": {"next_screen": "FullPaymentRouter-RW", "menus_that_points_to_this_menu": ["FullPaymentLoanTypeR-RW"]}}, "http://ussd:8092/loan/v1/limit": {"GeneralPurposeLoanGetLimitFunction-RW": {"next_screen": "GeneralPurposeLoanGetLimitRouter-RW", "menus_that_points_to_this_menu": []}}, "http://ussd:8092/loan/v1/limitV2": {"OverdraftCheckloanLimitFunction-RW": {"next_screen": "OverdraftCheckloanLimitRouter-RW", "menus_that_points_to_this_menu": []}}, "http://ussd:8092/loan/v1/loan-v1/generalpurpose/apply": {"OverdraftApplication-RW": {"next_screen": "OverdraftApplicationRouter-RW", "menus_that_points_to_this_menu": []}}, "http://ussd:8092/loan/v1/loan-v1/generalpurpose/payoff": {"OverdraftLoanFullPayLoan-RW": {"next_screen": "OverdraftLoanPayLoanRouter-RW", "menus_that_points_to_this_menu": []}}, "http://ussd:8092/loan/v1/loanInstallmentOptions": {"GeneralPurposeV2InstallmentOptionsFu-RW": {"next_screen": "GeneralPurpInstallmentOptionsRouter-RW", "menus_that_points_to_this_menu": ["GeneralPurposeV2SelectAccount-RW"]}}, "http://ussd:8092/loan/v1/loan_prodcut_query": {"DynamicRepayableF-RW": {"next_screen": "DynamicRepayableR-RW", "menus_that_points_to_this_menu": []}}, "http://ussd:8092/loan/v1/loan_purposes": {"GeneralPurposeV2LoanPurpose-RW": {"next_screen": "GeneralPurposeV2LoanPurposeRouter-RW", "menus_that_points_to_this_menu": ["GeneralPurposeV2InstallmentOptions-RW", "GPLoansInstalmentsWithBalancev2-RW"]}}, "http://ussd:8092/loan/v1/merchant/apply": {"MerchantLoanGetLoanFunction-RW": {"next_screen": "MerchantLoanGetLoanRouter-RW", "menus_that_points_to_this_menu": []}}, "http://ussd:8092/loan/v1/merchant/loanlimit": {"MerchantLoanGetLoanLimitFunction-RW": {"next_screen": "MerchantLoanGetLoanLimitRouter-RW", "menus_that_points_to_this_menu": []}}, "http://ussd:8092/loan/v1/partialpayment": {"OverdraftLoanPartialPayLoan-RW": {"next_screen": "OverdraftLoanPayLoanRouter-RW", "menus_that_points_to_this_menu": []}}, "http://ussd:8092/loan/v1/partialpayment2": {"GPPartialRepaymentF-RW": {"next_screen": "GPRepaymentR-RW", "menus_that_points_to_this_menu": []}}, "http://ussd:8092/loan/v1/products": {"FetchLoanProducts-RW": {"next_screen": "ShowLoanProducts-RW", "menus_that_points_to_this_menu": []}}, "http://ussd:8092/loan/v1/totalRepayable": {"GeneralPurposeTotalPayable-RW": {"next_screen": "GeneralPurposePayableRouter-RW", "menus_that_points_to_this_menu": ["GeneralPurposeSelectAccountToDeposit-RW"]}}, "http://ussd:8092/loan/v1/totalRepayableV2": {"OverdraftTotalRepayable-RW": {"next_screen": "OverdraftTotalRepayableRouter-RW", "menus_that_points_to_this_menu": []}}, "http://ussd:8092/mobilemoney/v1/buyMpesaFloat": {"BuyMpesaFloatFunction-RW": {"next_screen": "BuyMpesaFloatRouter-RW", "menus_that_points_to_this_menu": []}}, "http://ussd:8092/mobilemoney/v1/buyMpesaFloatNameCheck": {"NameChecekFloatAgent-RW": {"next_screen": "NameCheckFloatRouter-RW", "menus_that_points_to_this_menu": ["FLoatAgentNumber-RW"]}}, "http://ussd:8092/mobilemoney/v1/getMobileMoneyTelcos": {"SCFetchMobileMoneyTelcos-RW": {"next_screen": "SCFetchMobileMoneyTelcosRouter-RW", "menus_that_points_to_this_menu": []}}, "http://ussd:8092/mobilemoney/v1/mobile/money": {"SendTkashFunction-RW": {"next_screen": "SendTkashRouter-RW", "menus_that_points_to_this_menu": []}}, "http://ussd:8092/mobilemoney/v1/mobile/money/charges": {"SCGetMobileMoneyCharges-RW": {"next_screen": "SCGetMobileMoneyChargesRouter-RW", "menus_that_points_to_this_menu": ["SCMobileMoneyAmountScreen-RW"]}}, "http://ussd:8092/mobilemoney/v1/namecheck": {"WalletFavouriteNameCheck-RW": {"next_screen": "WalletFavNameCheckRouter-RW", "menus_that_points_to_this_menu": ["WalletfavoriteAlias-RW"]}}, "http://ussd:8092/mobilemoney/v1/send/mobile/money": {"SCSendMobileMoneyFunction-RW": {"next_screen": "SCSendMobileMoneyRouter-RW", "menus_that_points_to_this_menu": []}}, "http://ussd:8092/onboarding/v1/registration/status": {"SCCheckRegistrationScreen-RW": {"next_screen": "SCValidateRegistration-RW", "menus_that_points_to_this_menu": ["initial_screensc-RW"]}}, "http://ussd:8092/onboarding/v1/signup": {"RegisterCustomerScreen-RW": {"next_screen": "ConfirmRegistrationScreen-RW", "menus_that_points_to_this_menu": ["ClientTokenSceeen-RW"]}}, "http://ussd:8092/settings/v1/bank": {"FetchAllBanksFS-RW": {"next_screen": "ShowAllBanksRS-RW", "menus_that_points_to_this_menu": ["BankSearchScreenIN-RW"]}}, "http://ussd:8092/settings/v1/changePin": {"CompleteChangePIN-RW": {"next_screen": "CompleteChangePINRouter-RW", "menus_that_points_to_this_menu": []}}, "http://ussd:8092/settings/v1/changeTempPin": {"ChangeTemporaryPinFunction-RW": {"next_screen": "ChangeTemporaryPinRouter-RW", "menus_that_points_to_this_menu": ["changeTempPinPinTokenScreen-RW"]}}, "http://ussd:8092/settings/v1/initiateChangePin": {"ChangePINFunctionMenu-RW": {"next_screen": "InitiateChangePINRouter-RW", "menus_that_points_to_this_menu": []}}, "http://ussd:8092/settings/v1/lookup/bankcode": {"AddOtherAccBankLookUpF-RW": {"next_screen": "AddOtherAccBankLookUpR-RW", "menus_that_points_to_this_menu": []}}, "http://ussd:8092/settings/v1/lookup/banks": {"FetchKenyaBanks-RW": {"next_screen": "KenyaBanksRouter-RW", "menus_that_points_to_this_menu": []}}, "http://ussd:8092/settings/v1/securityQuestions": {"SecurityQuestionFunction-RW": {"next_screen": "SecurityQuestionRouter-RW", "menus_that_points_to_this_menu": []}}, "http://ussd:8092/settings/v1/sendsms": {"SendMiniStatementSMSFS-RW": {"next_screen": "SendMiniStatementSMSR-RW", "menus_that_points_to_this_menu": []}}, "http://ussd:8092/settings/v1/token": {"FetchKenyaWallets-RW": {"next_screen": "ShowKenyaWalllets-RW", "menus_that_points_to_this_menu": []}}, "http://ussd:8092/settings/v1/verifyTempPin": {"VerifyTemporaryPinFunction-RW": {"next_screen": "ValidateTempPinRouter-RW", "menus_that_points_to_this_menu": ["verifyTempPinTokenScreen-RW"]}}, "http://ussd:8092/transfer/v1/inter": {"OtherBanksTransferPhoneFunction-RW": {"next_screen": "OtherBankTransfRouter-RW", "menus_that_points_to_this_menu": []}}, "http://ussd:8092/transfer/v1/intra": {"FtEquityFavoriteFunction-RW": {"next_screen": "RouterFtEquityFavoriteFunction-RW", "menus_that_points_to_this_menu": []}}, "http://ussd:8092/transfer/v1/pesalink/query": {"PhoneAssociatedBanksFunctionScreen-RW": {"next_screen": "PhoneAssociatedBanksRouterScreen-RW", "menus_that_points_to_this_menu": ["OtherBankPhonePaymentReason-RW"]}}, "http://ussd:8092/transfer/v1/transaction_charges": {"SCIntraBanksTransferCharge-RW": {"next_screen": "SCIntraBankTransferChargeRouter-RW", "menus_that_points_to_this_menu": []}}, "http://ussd:8092/withdraw/v1/agentcharges": {"AgentWithdrawChargesFunction-RW": {"next_screen": "AgentWithdrawChargesRouter-RW", "menus_that_points_to_this_menu": ["DynamicSelectAccount-RW"]}}, "http://ussd:8092/withdraw/v1/atm": {"WithdrawATMF-RW": {"next_screen": "WithdrawATMR-RW", "menus_that_points_to_this_menu": []}}}